ezgit/.gitignore
ezgit/__init__.py
ezgit/ezgit.py
ezgit-0.1.0.dist-info/entry_points.txt
ezgit-0.1.0.dist-info/LICENSE
ezgit-0.1.0.dist-info/WHEEL
ezgit-0.1.0.dist-info/METADATA
ezgit-0.1.0.dist-info/RECORD
